easyfile_pro/__init__.py
easyfile_pro-0.1.5.dist-info/LICENSE.txt
easyfile_pro-0.1.5.dist-info/METADATA
easyfile_pro-0.1.5.dist-info/WHEEL
easyfile_pro-0.1.5.dist-info/top_level.txt
easyfile_pro-0.1.5.dist-info/RECORD
