Metadata-Version: 2.1
Name: easyfile-pro
Version: 0.1.5
Summary: =======easyfile_pro，you can easy to operate files now=======
Home-page: UNKNOWN
Author: yangqi
Author-email: geekpaul@outlook.com
License: MIT Licence
Keywords: os,tool,file
Platform: any
